wassgridsurface/DCTInterpolator.py
wassgridsurface/IDWInterpolator.py
wassgridsurface/TFVariationalRefinement.py
wassgridsurface/__init__.py
wassgridsurface/__main__.py
wassgridsurface/netcdfoutput.py
wassgridsurface/wass_utils.py
wassgridsurface/wassgridsurface.py
wassgridsurface-0.11.4.dist-info/METADATA
wassgridsurface-0.11.4.dist-info/WHEEL
wassgridsurface-0.11.4.dist-info/entry_points.txt
wassgridsurface-0.11.4.dist-info/top_level.txt
wassgridsurface-0.11.4.dist-info/RECORD
